README.md
setup.py
bulknlp/DamerauLevenshtein.c
bulknlp/__init__.py
bulknlp.egg-info/PKG-INFO
bulknlp.egg-info/SOURCES.txt
bulknlp.egg-info/dependency_links.txt
bulknlp.egg-info/requires.txt
bulknlp.egg-info/top_level.txt